pycrosaccade/__init__.py
pycrosaccade/_pycrosaccade.py
pycrosaccade-0.5.0.dist-info/WHEEL
pycrosaccade-0.5.0.dist-info/METADATA
pycrosaccade-0.5.0.dist-info/RECORD
