Metadata-Version: 2.1
Name: pycrosaccade
Version: 0.5.0
Summary: Detect microsaccades
Author-email: Robbert van der Mijn <robbertmijn@gmail.com>
Requires-Python: >=3.5
Classifier: License :: OSI Approved :: MIT License
Requires-Dist: datamatrix
Requires-Dist: numpy
Project-URL: Documentation, https://github.com/robbertmijn/pycrosaccade
Project-URL: Source, https://github.com/robbertmijn/pycrosaccade
